bayes_ordinal/__init__.py
bayes_ordinal/analysis/__init__.py
bayes_ordinal/analysis/counterfactual.py
bayes_ordinal/models/__init__.py
bayes_ordinal/models/cumulative.py
bayes_ordinal/utils/__init__.py
bayes_ordinal/utils/data_processing.py
bayes_ordinal/utils/model_inspection.py
bayes_ordinal/utils/model_validation.py
bayes_ordinal/workflow/__init__.py
bayes_ordinal/workflow/computation.py
bayes_ordinal/workflow/cross_validation.py
bayes_ordinal/workflow/diagnostics.py
bayes_ordinal/workflow/fitting.py
bayes_ordinal/workflow/posterior_predictive.py
bayes_ordinal/workflow/prior_predictive.py
bayes_ordinal/workflow/sensitivity.py
bayes_ordinal-0.1.0.dist-info/licenses/LICENSE
bayes_ordinal-0.1.0.dist-info/METADATA
bayes_ordinal-0.1.0.dist-info/WHEEL
bayes_ordinal-0.1.0.dist-info/top_level.txt
bayes_ordinal-0.1.0.dist-info/RECORD
