Metadata-Version: 2.4
Name: bayes-ordinal
Version: 0.1.0
Summary: A PyMC-based package for Bayesian ordinal regression with comprehensive workflow tools
Author-email: Adithyan Annadurai <3004787a@student.gla.ac.uk>
License: MIT
Project-URL: Homepage, https://github.com/Adithyanpy/bayes-ordinal
Project-URL: Repository, https://github.com/Adithyanpy/bayes-ordinal
Project-URL: Issues, https://github.com/Adithyanpy/bayes-ordinal/issues
Keywords: bayesian,ordinal-regression,pymc,arviz,statistics
Classifier: Development Status :: 3 - Alpha
Classifier: Intended Audience :: Science/Research
Classifier: License :: OSI Approved :: MIT License
Classifier: Programming Language :: Python :: 3
Classifier: Programming Language :: Python :: 3.11
Classifier: Topic :: Scientific/Engineering
Requires-Python: >=3.11
License-File: LICENSE
Requires-Dist: numpy==1.26.4
Requires-Dist: scipy==1.11.4
Requires-Dist: pymc==5.19.0
Requires-Dist: arviz==0.19.0
Requires-Dist: xarray==2023.12.0
Requires-Dist: matplotlib==3.10.5
Requires-Dist: pandas==2.3.1
Requires-Dist: scikit-learn==1.7.1
Requires-Dist: PyYAML==6.0.2
Provides-Extra: dev
Requires-Dist: ipykernel==6.30.0; extra == "dev"
Requires-Dist: jupyterlab>=4.1; extra == "dev"
Requires-Dist: pytest>=7.4; extra == "dev"
Requires-Dist: black>=23.9; extra == "dev"
Requires-Dist: pre-commit>=3.4; extra == "dev"
Dynamic: license-file
